[
   {
      "State": "State - JAMMU & KASHMIR",
      "Male": 401279,
      "Female": 252485
   },
   {
      "State": "State - HIMACHAL PRADESH",
      "Male": 251164,
      "Female": 195445
   },
   {
      "State": "State - PUNJAB",
      "Male": 873776,
      "Female": 887070
   },
   {
      "State": "State - CHANDIGARH",
      "Male": 104748,
      "Female": 89705
   },
   {
      "State": "State - UTTARAKHAND",
      "Male": 512068,
      "Female": 398220
   },
   {
      "State": "State - HARYANA",
      "Male": 1102809,
      "Female": 774276
   },
   {
      "State": "State - NCT OF DELHI",
      "Male": 1535972,
      "Female": 1221872
   },
   {
      "State": "State - RAJASTHAN",
      "Male": 2086247,
      "Female": 977035
   },
   {
      "State": "State - UTTAR PRADESH",
      "Male": 6378138,
      "Female": 3541700
   },
   {
      "State": "State - BIHAR",
      "Male": 2326092,
      "Female": 735584
   },
   {
      "State": "State - SIKKIM",
      "Male": 19290,
      "Female": 13379
   },
   {
      "State": "State - ARUNACHAL PRADESH",
      "Male": 36430,
      "Female": 17176
   },
   {
      "State": "State - NAGALAND",
      "Male": 53023,
      "Female": 36695
   },
   {
      "State": "State - MANIPUR",
      "Male": 135082,
      "Female": 90538
   },
   {
      "State": "State - MIZORAM",
      "Male": 29527,
      "Female": 20094
   },
   {
      "State": "State - TRIPURA",
      "Male": 88621,
      "Female": 49191
   },
   {
      "State": "State - MEGHALAYA",
      "Male": 46311,
      "Female": 44208
   },
   {
      "State": "State - ASSAM",
      "Male": 639241,
      "Female": 372104
   },
   {
      "State": "State - WEST BENGAL",
      "Male": 3088673,
      "Female": 1739144
   },
   {
      "State": "State - JHARKHAND",
      "Male": 906174,
      "Female": 422303
   },
   {
      "State": "State - ODISHA",
      "Male": 1174184,
      "Female": 609613
   },
   {
      "State": "State - CHHATTISGARH",
      "Male": 659081,
      "Female": 359772
   },
   {
      "State": "State - MADHYA PRADESH",
      "Male": 2051127,
      "Female": 1171675
   },
   {
      "State": "State - GUJARAT",
      "Male": 1891932,
      "Female": 1282226
   },
   {
      "State": "State - DAMAN & DIU",
      "Male": 8425,
      "Female": 4377
   },
   {
      "State": "State - DADRA & NAGAR HAVELI",
      "Male": 12227,
      "Female": 6947
   },
   {
      "State": "State - MAHARASHTRA",
      "Male": 5167671,
      "Female": 3471410
   },
   {
      "State": "State - ANDHRA PRADESH",
      "Male": 3632622,
      "Female": 1944765
   },
   {
      "State": "State - KARNATAKA",
      "Male": 2489209,
      "Female": 1554438
   },
   {
      "State": "State - GOA",
      "Male": 74077,
      "Female": 72751
   },
   {
      "State": "State - LAKSHADWEEP",
      "Male": 1458,
      "Female": 844
   },
   {
      "State": "State - KERALA",
      "Male": 1131336,
      "Female": 1399985
   },
   {
      "State": "State - TAMIL NADU",
      "Male": 3119342,
      "Female": 2338400
   },
   {
      "State": "State - PUDUCHERRY",
      "Male": 79482,
      "Female": 62547
   },
   {
      "State": "State - ANDAMAN & NICOBAR ISLANDS",
      "Male": 13622,
      "Female": 10537
   }
]